[
    {
        "name": "Rebok StealthKick",
        "price": 158,
        "availableSizes": [
            11,
            10,
            8,
            12,
            7
        ],
        "description": "Limited edition sneaker for streetwear lovers.",
        "colors": [
            {
                "color": "Grey",
                "image": "https://placehold.co/400x400/808080/FFFFFF?text=Rebok+StealthKick"
            },
            {
                "color": "Green",
                "image": "https://placehold.co/400x400/00FF00/FFFFFF?text=Rebok+StealthKick"
            },
            {
                "color": "Black",
                "image": "https://placehold.co/400x400/000000/FFFFFF?text=Rebok+StealthKick"
            }
        ],
        "stock": 44,
        "category": "sneakers"
    },
    {
        "name": "PumaX FlexZoom",
        "price": 201,
        "availableSizes": [
            11,
            8,
            6,
            10,
            12
        ],
        "description": "High-performance running shoe with breathable mesh.",
        "colors": [
            {
                "color": "White",
                "image": "https://placehold.co/400x400/FFFFFF/FFFFFF?text=PumaX+FlexZoom"
            },
            {
                "color": "Green",
                "image": "https://placehold.co/400x400/00FF00/FFFFFF?text=PumaX+FlexZoom"
            },
            {
                "color": "Black",
                "image": "https://placehold.co/400x400/000000/FFFFFF?text=PumaX+FlexZoom"
            }
        ],
        "stock": 9,
        "category": "sneakers"
    },
    {
        "name": "Dripster StealthKick",
        "price": 209,
        "availableSizes": [
            9,
            7,
            8,
            10,
            11
        ],
        "description": "High-performance running shoe with breathable mesh.",
        "colors": [
            {
                "color": "Blue",
                "image": "https://placehold.co/400x400/0000FF/FFFFFF?text=Dripster+StealthKick"
            },
            {
                "color": "Orange",
                "image": "https://placehold.co/400x400/FFA500/FFFFFF?text=Dripster+StealthKick"
            },
            {
                "color": "Red",
                "image": "https://placehold.co/400x400/FF0000/FFFFFF?text=Dripster+StealthKick"
            }
        ],
        "stock": 41,
        "category": "sneakers"
    },
    {
        "name": "PumaX StealthKick",
        "price": 145,
        "availableSizes": [
            7,
            12,
            11,
            6,
            8
        ],
        "description": "Lightweight sneaker designed for daily wear.",
        "colors": [
            {
                "color": "Black",
                "image": "https://placehold.co/400x400/000000/FFFFFF?text=PumaX+StealthKick"
            },
            {
                "color": "Grey",
                "image": "https://placehold.co/400x400/808080/FFFFFF?text=PumaX+StealthKick"
            },
            {
                "color": "White",
                "image": "https://placehold.co/400x400/FFFFFF/FFFFFF?text=PumaX+StealthKick"
            }
        ],
        "stock": 37,
        "category": "sneakers"
    },
    {
        "name": "Adynas AirMax",
        "price": 152,
        "availableSizes": [
            7,
            11,
            12,
            6,
            9
        ],
        "description": "Performance-focused design with cushioned sole.",
        "colors": [
            {
                "color": "Grey",
                "image": "https://placehold.co/400x400/808080/FFFFFF?text=Adynas+AirMax"
            },
            {
                "color": "Orange",
                "image": "https://placehold.co/400x400/FFA500/FFFFFF?text=Adynas+AirMax"
            },
            {
                "color": "White",
                "image": "https://placehold.co/400x400/FFFFFF/FFFFFF?text=Adynas+AirMax"
            }
        ],
        "stock": 39,
        "category": "sneakers"
    },
    {
        "name": "Zyke BoostX",
        "price": 171,
        "availableSizes": [
            12,
            8,
            9,
            6,
            11
        ],
        "description": "High-performance running shoe with breathable mesh.",
        "colors": [
            {
                "color": "Orange",
                "image": "https://placehold.co/400x400/FFA500/FFFFFF?text=Zyke+BoostX"
            },
            {
                "color": "Blue",
                "image": "https://placehold.co/400x400/0000FF/FFFFFF?text=Zyke+BoostX"
            },
            {
                "color": "White",
                "image": "https://placehold.co/400x400/FFFFFF/FFFFFF?text=Zyke+BoostX"
            }
        ],
        "stock": 23,
        "category": "sneakers"
    },
    {
        "name": "Rebok StealthKick",
        "price": 147,
        "availableSizes": [
            12,
            6,
            10,
            11,
            9
        ],
        "description": "Limited edition sneaker for streetwear lovers.",
        "colors": [
            {
                "color": "Black",
                "image": "https://placehold.co/400x400/000000/FFFFFF?text=Rebok+StealthKick"
            },
            {
                "color": "Blue",
                "image": "https://placehold.co/400x400/0000FF/FFFFFF?text=Rebok+StealthKick"
            },
            {
                "color": "Red",
                "image": "https://placehold.co/400x400/FF0000/FFFFFF?text=Rebok+StealthKick"
            }
        ],
        "stock": 28,
        "category": "sneakers"
    },
    {
        "name": "PumaX UltraRun",
        "price": 213,
        "availableSizes": [
            11,
            12,
            8,
            6,
            7
        ],
        "description": "High-performance running shoe with breathable mesh.",
        "colors": [
            {
                "color": "Green",
                "image": "https://placehold.co/400x400/00FF00/FFFFFF?text=PumaX+UltraRun"
            },
            {
                "color": "Grey",
                "image": "https://placehold.co/400x400/808080/FFFFFF?text=PumaX+UltraRun"
            },
            {
                "color": "Red",
                "image": "https://placehold.co/400x400/FF0000/FFFFFF?text=PumaX+UltraRun"
            }
        ],
        "stock": 32,
        "category": "sneakers"
    },
    {
        "name": "Sneako UltraRun",
        "price": 92,
        "availableSizes": [
            12,
            8,
            6,
            11,
            7
        ],
        "description": "Built for comfort and speed with sleek design.",
        "colors": [
            {
                "color": "Red",
                "image": "https://placehold.co/400x400/FF0000/FFFFFF?text=Sneako+UltraRun"
            },
            {
                "color": "Black",
                "image": "https://placehold.co/400x400/000000/FFFFFF?text=Sneako+UltraRun"
            },
            {
                "color": "Grey",
                "image": "https://placehold.co/400x400/808080/FFFFFF?text=Sneako+UltraRun"
            }
        ],
        "stock": 41,
        "category": "sneakers"
    },
    {
        "name": "Sneako UltraRun",
        "price": 80,
        "availableSizes": [
            11,
            12,
            10,
            9,
            6
        ],
        "description": "Lightweight sneaker designed for daily wear.",
        "colors": [
            {
                "color": "Black",
                "image": "https://placehold.co/400x400/000000/FFFFFF?text=Sneako+UltraRun"
            },
            {
                "color": "Blue",
                "image": "https://placehold.co/400x400/0000FF/FFFFFF?text=Sneako+UltraRun"
            },
            {
                "color": "Grey",
                "image": "https://placehold.co/400x400/808080/FFFFFF?text=Sneako+UltraRun"
            }
        ],
        "stock": 25,
        "category": "sneakers"
    },
    {
        "name": "PumaX BoostX",
        "price": 126,
        "availableSizes": [
            9,
            6,
            12,
            11,
            8
        ],
        "description": "Built for comfort and speed with sleek design.",
        "colors": [
            {
                "color": "Orange",
                "image": "https://placehold.co/400x400/FFA500/FFFFFF?text=PumaX+BoostX"
            },
            {
                "color": "Grey",
                "image": "https://placehold.co/400x400/808080/FFFFFF?text=PumaX+BoostX"
            },
            {
                "color": "Blue",
                "image": "https://placehold.co/400x400/0000FF/FFFFFF?text=PumaX+BoostX"
            }
        ],
        "stock": 20,
        "category": "sneakers"
    },
    {
        "name": "Sneako Phantom",
        "price": 135,
        "availableSizes": [
            10,
            6,
            12,
            8,
            11
        ],
        "description": "Built for comfort and speed with sleek design.",
        "colors": [
            {
                "color": "Blue",
                "image": "https://placehold.co/400x400/0000FF/FFFFFF?text=Sneako+Phantom"
            },
            {
                "color": "Green",
                "image": "https://placehold.co/400x400/00FF00/FFFFFF?text=Sneako+Phantom"
            },
            {
                "color": "Red",
                "image": "https://placehold.co/400x400/FF0000/FFFFFF?text=Sneako+Phantom"
            }
        ],
        "stock": 7,
        "category": "sneakers"
    },
    {
        "name": "Rebok FlexZoom",
        "price": 94,
        "availableSizes": [
            7,
            12,
            6,
            9,
            8
        ],
        "description": "Limited edition sneaker for streetwear lovers.",
        "colors": [
            {
                "color": "Grey",
                "image": "https://placehold.co/400x400/808080/FFFFFF?text=Rebok+FlexZoom"
            },
            {
                "color": "White",
                "image": "https://placehold.co/400x400/FFFFFF/FFFFFF?text=Rebok+FlexZoom"
            },
            {
                "color": "Blue",
                "image": "https://placehold.co/400x400/0000FF/FFFFFF?text=Rebok+FlexZoom"
            }
        ],
        "stock": 13,
        "category": "sneakers"
    },
    {
        "name": "Dripster FlexZoom",
        "price": 112,
        "availableSizes": [
            12,
            9,
            10,
            11,
            8
        ],
        "description": "High-performance running shoe with breathable mesh.",
        "colors": [
            {
                "color": "Grey",
                "image": "https://placehold.co/400x400/808080/FFFFFF?text=Dripster+FlexZoom"
            },
            {
                "color": "White",
                "image": "https://placehold.co/400x400/FFFFFF/FFFFFF?text=Dripster+FlexZoom"
            },
            {
                "color": "Green",
                "image": "https://placehold.co/400x400/00FF00/FFFFFF?text=Dripster+FlexZoom"
            }
        ],
        "stock": 14,
        "category": "sneakers"
    },
    {
        "name": "Dripster StealthKick",
        "price": 204,
        "availableSizes": [
            9,
            10,
            11,
            6,
            12
        ],
        "description": "High-performance running shoe with breathable mesh.",
        "colors": [
            {
                "color": "White",
                "image": "https://placehold.co/400x400/FFFFFF/FFFFFF?text=Dripster+StealthKick"
            },
            {
                "color": "Orange",
                "image": "https://placehold.co/400x400/FFA500/FFFFFF?text=Dripster+StealthKick"
            },
            {
                "color": "Blue",
                "image": "https://placehold.co/400x400/0000FF/FFFFFF?text=Dripster+StealthKick"
            }
        ],
        "stock": 18,
        "category": "sneakers"
    }
]